bapipe/__init__.py
bapipe/api.py
bapipe/configs.py
bapipe/utils.py
bapipe_keypoints_telfer-0.1.0.dist-info/LICENSE
bapipe_keypoints_telfer-0.1.0.dist-info/METADATA
bapipe_keypoints_telfer-0.1.0.dist-info/WHEEL
bapipe_keypoints_telfer-0.1.0.dist-info/top_level.txt
bapipe_keypoints_telfer-0.1.0.dist-info/RECORD
