Metadata-Version: 2.1
Name: bapipe-keypoints-telfer
Version: 0.1.0
Summary: Behavioural Analysis with Keypoints Data
Home-page: https://github.com/A-Telfer/bapipe-keypoints
Author: Andre Telfer
Author-email: andretelfer@cmail.carleton.ca
Project-URL: Bug Tracker, https://github.com/A-Telfer/bapipe-keypoints/issues
Classifier: Programming Language :: Python :: 3
Classifier: License :: OSI Approved :: MIT License
Classifier: Operating System :: OS Independent
Requires-Python: >=3.6
License-File: LICENSE
Requires-Dist: opencv-python (>=4)
Requires-Dist: numpy
Requires-Dist: pandas
Requires-Dist: matplotlib
Requires-Dist: ffmpeg-python
